LICENSE
README.md
setup.cfg
setup.py
sprint_toolkit/__init__.py
sprint_toolkit.egg-info/PKG-INFO
sprint_toolkit.egg-info/SOURCES.txt
sprint_toolkit.egg-info/dependency_links.txt
sprint_toolkit.egg-info/requires.txt
sprint_toolkit.egg-info/top_level.txt
sprint_toolkit/inference/__init__.py
sprint_toolkit/inference/aio.py
sprint_toolkit/inference/data_iters.py
sprint_toolkit/inference/encode.py
sprint_toolkit/inference/encoder_builders.py
sprint_toolkit/inference/evaluate.py
sprint_toolkit/inference/index.py
sprint_toolkit/inference/logging.py
sprint_toolkit/inference/quantize.py
sprint_toolkit/inference/reformat_query.py
sprint_toolkit/inference/rerank.py
sprint_toolkit/inference/search.py
sprint_toolkit/inference/utils.py
sprint_toolkit/inference/methods/__init__.py
sprint_toolkit/inference/methods/deepimpact.py
sprint_toolkit/inference/methods/sparta.py
sprint_toolkit/inference/methods/splade.py
sprint_toolkit/inference/methods/tildev2.py
sprint_toolkit/inference/methods/unicoil.py
sprint_toolkit/train/__init__.py
sprint_toolkit/train/trainer.py
sprint_toolkit/train/dataloaders/MSMARCODataLoader.py
sprint_toolkit/train/dataloaders/MSMARCOGroupedDataLoader.py
sprint_toolkit/train/dataloaders/__init__.py
sprint_toolkit/train/losses/MarginMSELoss.py
sprint_toolkit/train/losses/MultipleNegativeRankingLoss.py
sprint_toolkit/train/losses/__init__.py
sprint_toolkit/train/losses/utils.py
sprint_toolkit/train/models/__init__.py
sprint_toolkit/train/models/deepimpact.py
sprint_toolkit/train/models/sparta.py
sprint_toolkit/train/models/splade.py
sprint_toolkit/train/models/tilde.py
sprint_toolkit/train/models/unicoil.py
sprint_toolkit/train/models/utils.py