Metadata-Version: 2.1
Name: sprint-toolkit
Version: 0.0.2
Summary: SPRINT: A Unified Toolkit for Evaluating and Demystifying Zero-shot Neural Sparse Retrieval
Home-page: https://github.com/thakur-nandan/sprint
Author: Nandan Thakur
Author-email: nandant@gmail.com
Project-URL: Bug Tracker, https://github.com/thakur-nandan/sprint/issues
Keywords: Information Retrieval Toolkit Sparse Retrievers Networks BERT PyTorch IR NLP deep learning
Classifier: Programming Language :: Python :: 3.8
Classifier: License :: OSI Approved :: Apache Software License
Classifier: Operating System :: OS Independent
Classifier: Topic :: Scientific/Engineering :: Artificial Intelligence
Classifier: Intended Audience :: Science/Research
Requires-Python: >=3.7
License-File: LICENSE
